PA_PYPI/__init__.py
PA_PYPI/mini-opencode/__init__.py
PA_PYPI/rag_qa_extract/__init__.py
pa_pypi-0.0.5.dist-info/licenses/LICENSE
pa_pypi-0.0.5.dist-info/METADATA
pa_pypi-0.0.5.dist-info/WHEEL
pa_pypi-0.0.5.dist-info/top_level.txt
pa_pypi-0.0.5.dist-info/RECORD
