Metadata-Version: 2.4
Name: pa_pypi
Version: 0.0.5
Summary: 这是一个用于演示上传PyPI的测试Python包
Author-email: zhongp <your_email@example.com>
Classifier: Programming Language :: Python :: 3
Classifier: License :: OSI Approved :: MIT License
Classifier: Operating System :: OS Independent
Requires-Python: >=3.7
License-File: LICENSE
Dynamic: license-file
